IronMQ.py
sd_ironmq-0.1.2.dist-info/DESCRIPTION.rst
sd_ironmq-0.1.2.dist-info/METADATA
sd_ironmq-0.1.2.dist-info/RECORD
sd_ironmq-0.1.2.dist-info/WHEEL
sd_ironmq-0.1.2.dist-info/metadata.json
sd_ironmq-0.1.2.dist-info/top_level.txt
