Metadata-Version: 2.0
Name: sd-ironmq
Version: 0.1.2
Summary: Server Density plugin to monitor IronMQs
Home-page: https://github.com/engagespark/sd-ironmq
Author: Murat Knecht
Author-email: muratk@engagespark.com
License: MIT
Platform: UNKNOWN
Classifier: Development Status :: 4 - Beta
Classifier: Programming Language :: Python
Requires-Dist: iron-mq-v3
Requires-Dist: requests
